{
  "project_info": {
    "project_number": "951992710429",
    "firebase_url": "https://quickfix-303414-default-rtdb.firebaseio.com",
    "project_id": "quickfix-303414",
    "storage_bucket": "quickfix-303414.appspot.com"
  },
  "client": [
    {
      "client_info": {
        "mobilesdk_app_id": "1:951992710429:android:acf421dd16414fc4041df4",
        "android_client_info": {
          "package_name": "com.example.quickfixuser"
        }
      },
      "oauth_client": [
        {
          "client_id": "951992710429-nbsrjnaip0qsbcd5rm9sksf7bngs66hc.apps.googleusercontent.com",
          "client_type": 3
        }
      ],
      "api_key": [
        {
          "current_key": "AIzaSyBC190lBVPfaR0AH_YM9WaN8ACmECRQQ-g"
        }
      ],
      "services": {
        "appinvite_service": {
          "other_platform_oauth_client": [
            {
              "client_id": "951992710429-nbsrjnaip0qsbcd5rm9sksf7bngs66hc.apps.googleusercontent.com",
              "client_type": 3
            }
          ]
        }
      }
    },
    {
      "client_info": {
        "mobilesdk_app_id": "1:951992710429:android:8239498bae5f4964041df4",
        "android_client_info": {
          "package_name": "com.example.quickfixvehicle"
        }
      },
      "oauth_client": [
        {
          "client_id": "951992710429-o94ask38u5k3vcmm1dp6bfid84k6vd7r.apps.googleusercontent.com",
          "client_type": 1,
          "android_info": {
            "package_name": "com.example.quickfixvehicle",
            "certificate_hash": "1a766226b9e6a87bd5fb01d9ea1896325f583328"
          }
        },
        {
          "client_id": "951992710429-nbsrjnaip0qsbcd5rm9sksf7bngs66hc.apps.googleusercontent.com",
          "client_type": 3
        }
      ],
      "api_key": [
        {
          "current_key": "AIzaSyBC190lBVPfaR0AH_YM9WaN8ACmECRQQ-g"
        }
      ],
      "services": {
        "appinvite_service": {
          "other_platform_oauth_client": [
            {
              "client_id": "951992710429-nbsrjnaip0qsbcd5rm9sksf7bngs66hc.apps.googleusercontent.com",
              "client_type": 3
            }
          ]
        }
      }
    },
    {
      "client_info": {
        "mobilesdk_app_id": "1:951992710429:android:4556e74c56f014d1041df4",
        "android_client_info": {
          "package_name": "com.temp.driversapp"
        }
      },
      "oauth_client": [
        {
          "client_id": "951992710429-nbsrjnaip0qsbcd5rm9sksf7bngs66hc.apps.googleusercontent.com",
          "client_type": 3
        }
      ],
      "api_key": [
        {
          "current_key": "AIzaSyBC190lBVPfaR0AH_YM9WaN8ACmECRQQ-g"
        }
      ],
      "services": {
        "appinvite_service": {
          "other_platform_oauth_client": [
            {
              "client_id": "951992710429-nbsrjnaip0qsbcd5rm9sksf7bngs66hc.apps.googleusercontent.com",
              "client_type": 3
            }
          ]
        }
      }
    }
  ],
  "configuration_version": "1"
}